hairgap/__init__.py
hairgap/cli.py
hairgap/constants.py
hairgap/receiver.py
hairgap/sender.py
hairgap/tests/__init__.py
hairgap/tests/hairgapr.py
hairgap/tests/hairgaps.py
hairgap/tests/test_protocol.py
hairgap/tests/test_sender.py
hairgap/tests/test_utils.py
hairgap/utils.py
hairgap-1.2.2.dist-info/LICENSE
hairgap-1.2.2.dist-info/METADATA
hairgap-1.2.2.dist-info/WHEEL
hairgap-1.2.2.dist-info/entry_points.txt
hairgap-1.2.2.dist-info/RECORD
